setup.cfg
setup.py
Reconsider/__init__.py
reconsider.egg-info/PKG-INFO
reconsider.egg-info/SOURCES.txt
reconsider.egg-info/dependency_links.txt
reconsider.egg-info/requires.txt
reconsider.egg-info/top_level.txt
reconsider.egg-info/zip-safe