Metadata-Version: 1.0
Name: reconsider
Version: 1.0.0
Summary: Reconsider is a module used to move DBs/Tables from one RethinkDB instance to another.
Home-page: https://github.com/ouroboroscoding/reconsider
Author: Chris Nasr - OuroborosCoding
Author-email: ouroboroscode@gmail.com
License: Apache-2.0
Keywords: rethinkdb,data,database,db,nosql
Platform: UNKNOWN
